CHANGELOG.rst
CONTRIBUTING.md
LICENSE
README.rst
pyproject.toml
sqlalchemy_initdb/__init__.py
sqlalchemy_initdb/__main__.py
sqlalchemy_initdb/cli.py
sqlalchemy_initdb/loaddata.py
sqlalchemy_initdb/py.typed
sqlalchemy_initdb-0.1.0.dist-info/LICENSE
sqlalchemy_initdb-0.1.0.dist-info/METADATA
sqlalchemy_initdb-0.1.0.dist-info/WHEEL
sqlalchemy_initdb-0.1.0.dist-info/entry_points.txt
sqlalchemy_initdb-0.1.0.dist-info/RECORD
