Metadata-Version: 2.1
Name: sqlalchemy-initdb
Version: 0.1.0
Summary: Django like fixtures for SQLAlchemy
Home-page: https://github.com/dnmellen/sqlalchemy-initdb
License: AGPL-3.0-only
Keywords: python package
Author: Diego Navarro
Author-email: dnmellen@gmail.com
Maintainer: Diego Navarro
Maintainer-email: dnmellen@gmail.com
Requires-Python: >=3.9,<4.0
Classifier: Development Status :: 5 - Production/Stable
Classifier: Intended Audience :: Developers
Classifier: Intended Audience :: End Users/Desktop
Classifier: Intended Audience :: Science/Research
Classifier: License :: OSI Approved :: GNU Affero General Public License v3
Classifier: Natural Language :: English
Classifier: Operating System :: MacOS
Classifier: Operating System :: POSIX :: Linux
Classifier: Operating System :: Unix
Classifier: Programming Language :: Python
Classifier: Programming Language :: Python :: 3
Classifier: Programming Language :: Python :: 3.9
Classifier: Programming Language :: Python :: 3.10
Classifier: Programming Language :: Python :: 3.11
Classifier: Programming Language :: Python :: 3.6
Classifier: Programming Language :: Python :: 3.7
Classifier: Programming Language :: Python :: 3.8
Classifier: Topic :: Software Development
Classifier: Topic :: Software Development :: Libraries :: Python Modules
Classifier: Topic :: System :: Software Distribution
Classifier: Typing :: Typed
Provides-Extra: docs
Provides-Extra: test
Provides-Extra: typing
Requires-Dist: mypy (==0.961) ; extra == "typing"
Requires-Dist: pytest (>=6.2.4) ; extra == "test" or extra == "typing"
Requires-Dist: pytest-click (>=1.1.0,<2.0.0) ; extra == "test" or extra == "typing"
Requires-Dist: pytest-cov (>=2.12) ; extra == "test"
Requires-Dist: pytest-explicit (>=1.0.1,<1.1.0) ; extra == "test"
Requires-Dist: pytest-xdist (>=1.34) ; extra == "test"
Requires-Dist: sphinx (>=4.0,<5.0) ; extra == "docs"
Requires-Dist: sphinx-autodoc-typehints (>=1.10) ; extra == "docs"
Requires-Dist: sphinx-rtd-theme (==0.5.0) ; extra == "docs"
Requires-Dist: sphinxcontrib-spelling (>=7.3.3,<7.4.0) ; extra == "docs"
Requires-Dist: sqlalchemy (>=2.0.14,<3.0.0)
Project-URL: Bug Tracker, https://github.com/sqlalchemy-initdb/issues
Project-URL: CI: Github Actions, https://github.com/dnmellen/sqlalchemy-initdb/actions
Project-URL: Changelog, https://github.com/dnmellen/sqlalchemy-initdb/blob/master/CHANGELOG.rst
Project-URL: Code of Conduct, https://github.com/dnmellen/sqlalchemy-initdb/blob/master/CONTRIBUTING.rst
Project-URL: Documentation, https://sqlalchemy-initdb.readthedocs.io/
Project-URL: Repository, https://github.com/dnmellen/sqlalchemy-initdb
Project-URL: Source Code, https://github.com/dnmellen/sqlalchemy-initdb
